.coveragerc
.gitignore
MANIFEST.in
README.rst
bootstrap.py
setup.cfg
setup.py
test-coverage.sh
test-plone-4.3.x.cfg
test-plone-5.0.x.cfg
test-plone-base.cfg
test-set-buildout.sh
docs/HISTORY.txt
docs/LICENSE.GPL
docs/LICENSE.txt
docs/collective-pfg-norobots-screenshot.png
src/collective/__init__.py
src/collective.pfg.norobots.egg-info/PKG-INFO
src/collective.pfg.norobots.egg-info/SOURCES.txt
src/collective.pfg.norobots.egg-info/dependency_links.txt
src/collective.pfg.norobots.egg-info/entry_points.txt
src/collective.pfg.norobots.egg-info/namespace_packages.txt
src/collective.pfg.norobots.egg-info/not-zip-safe
src/collective.pfg.norobots.egg-info/paster_plugins.txt
src/collective.pfg.norobots.egg-info/requires.txt
src/collective.pfg.norobots.egg-info/top_level.txt
src/collective/pfg/__init__.py
src/collective/pfg/norobots/__init__.py
src/collective/pfg/norobots/config.py
src/collective/pfg/norobots/configure.zcml
src/collective/pfg/norobots/field.py
src/collective/pfg/norobots/rebuild_i18n.sh
src/collective/pfg/norobots/testing.py
src/collective/pfg/norobots/widget.py
src/collective/pfg/norobots/Extensions/Install.py
src/collective/pfg/norobots/Extensions/__init__.py
src/collective/pfg/norobots/locales/collective.pfg.norobots.pot
src/collective/pfg/norobots/locales/manual.pot
src/collective/pfg/norobots/locales/en/LC_MESSAGES/collective.pfg.norobots.po
src/collective/pfg/norobots/locales/fr/LC_MESSAGES/collective.pfg.norobots.po
src/collective/pfg/norobots/locales/nl/LC_MESSAGES/collective.pfg.norobots.po
src/collective/pfg/norobots/profiles/default/cssregistry.xml
src/collective/pfg/norobots/profiles/default/factorytool.xml
src/collective/pfg/norobots/profiles/default/jsregistry.xml
src/collective/pfg/norobots/profiles/default/metadata.xml
src/collective/pfg/norobots/profiles/default/propertiestool.xml
src/collective/pfg/norobots/profiles/default/skins.xml
src/collective/pfg/norobots/profiles/default/types.xml
src/collective/pfg/norobots/profiles/default/workflows.xml
src/collective/pfg/norobots/profiles/default/types/FormFolder.xml
src/collective/pfg/norobots/profiles/default/types/FormNorobotsField.xml
src/collective/pfg/norobots/profiles/uninstall/cssregistry.xml
src/collective/pfg/norobots/profiles/uninstall/factorytool.xml
src/collective/pfg/norobots/profiles/uninstall/jsregistry.xml
src/collective/pfg/norobots/profiles/uninstall/metadata.xml
src/collective/pfg/norobots/profiles/uninstall/skins.xml
