Metadata-Version: 1.1
Name: collective.pfg.norobots
Version: 1.2
Summary: collective.pfg.norobots allows to add a collective.z3cform.norobots captcha field to PloneFormGen forms.
Home-page: https://github.com/sylvainb/collective.pfg.norobots
Author: Sylvain Boureliou [sylvainb]
Author-email: sylvain.boureliou@gmail.com
License: gpl
Keywords: plone web zope python ploneformgen field captcha
Platform: UNKNOWN
Classifier: Framework :: Plone
Classifier: Framework :: Plone :: 5.0
Classifier: Framework :: Plone :: 4.3
Classifier: Programming Language :: Python
Classifier: Programming Language :: Python :: 2.7
Classifier: Topic :: Software Development :: Libraries :: Python Modules
